Metadata-Version: 2.4
Name: confsec
Version: 0.1.5
Summary: Python SDK for Confident Security - secure and anonymous AI inference
Author-email: Confident Security <support@confidentsecurity.ai>
License: # Confident Security Limited License
Project-URL: Homepage, https://github.com/confidentsecurity/confsec-py
Project-URL: Documentation, https://github.com/confidentsecurity/confsec-py
Project-URL: Repository, https://github.com/confidentsecurity/confsec-py
Project-URL: Issues, https://github.com/confidentsecurity/confsec-py/issues
Keywords: ai,security,privacy,inference
Classifier: Development Status :: 4 - Beta
Classifier: Intended Audience :: Developers
Classifier: Operating System :: OS Independent
Classifier: Programming Language :: Python :: 3
Classifier: Programming Language :: Python :: 3.8
Classifier: Programming Language :: Python :: 3.9
Classifier: Programming Language :: Python :: 3.10
Classifier: Programming Language :: Python :: 3.11
Classifier: Programming Language :: Python :: 3.12
Classifier: Topic :: Software Development :: Libraries :: Python Modules
Classifier: Topic :: Security
Classifier: Topic :: Scientific/Engineering :: Artificial Intelligence
Requires-Python: >=3.8
License-File: LICENSE
Requires-Dist: openai>=1.0.0
Requires-Dist: httpx>=0.24.0
Requires-Dist: typing-extensions>=4.0.0
Provides-Extra: dev
Requires-Dist: pytest>=7.0.0; extra == "dev"
Requires-Dist: ruff>=0.12.0; extra == "dev"
Requires-Dist: mypy>=1.0.0; extra == "dev"
Requires-Dist: pre-commit>=3.0.0; extra == "dev"
Dynamic: license-file
